core_code/__init__.py
core_code/__main__.py
core_code/cli.py
core_code/models.py
core_code/storage.py
core_code/todo.json
core_code/utils.py
todo_eunho-0.1.2.dist-info/METADATA
todo_eunho-0.1.2.dist-info/WHEEL
todo_eunho-0.1.2.dist-info/entry_points.txt
todo_eunho-0.1.2.dist-info/top_level.txt
todo_eunho-0.1.2.dist-info/RECORD
