Metadata-Version: 2.4
Name: todo-eunho
Version: 0.1.2
Summary: A simple CLI todo manager
Author-email: Eunho Chung <silverhoo01@dgist.ac.kr>
License: MIT
Project-URL: Homepage, https://github.com/ChungEunho/CLI_Todo
Project-URL: Source, https://github.com/ChungEunho/CLI_Todo
Project-URL: Issues, https://github.com/ChungEunho/CLI_Todo/issues
Classifier: Programming Language :: Python :: 3
Classifier: License :: OSI Approved :: MIT License
Classifier: Operating System :: OS Independent
Classifier: Environment :: Console
Classifier: Intended Audience :: Developers
Classifier: Topic :: Utilities
Requires-Python: >=3.8
Requires-Dist: rich>=13.7.0
Requires-Dist: questionary>=2.0.1
